{
    "namespace": "activeSurgeDeployments",
    "strings": {
        "deployedEru": "Deployed ERU(s)",
        "surgeEruOnly": "Emergency Response Unit(ERU)",
        "surgePersonnelOnly": "Rapid Response Personnel(RR)",
        "eruAndPersonnel": "ERU & RR",
        "eruLabel": "ERU",
        "personnelLabel": "RR",
        "eventPopoverEmpty": "No Current Deployments",
        "deployedPersonnel": "Deployed Personnel",
        "surgeDownloadMapTitle": "Rapid Response Deployments",
        "explanationScalePoints": "Scale points by",
        "surgeMapTitle": "Active Deployments",
        "disasterTypeLabel": "Disaster Type",
        "disasterTypePlaceholder": "All Disaster Types",
        "surgeMechanismsLabel": "Surge Mechanism",
        "surgeMechanismsPlaceholder": "All Surge Mechanisms",
        "clearFilters": "Clear Filters",
        "emergencyResponseUnit": "Emergency Response Unit",
        "rapidResponsePersonnel": "Rapid Response Personnel",
        "eruType": "ERU Type(s)",
        "deployingNS": "Deploying NS",
        "roleProfile": "Role Profile(s)"

    }
}
